kriten_netbox/__init__.py
kriten_netbox/filtersets.py
kriten_netbox/forms.py
kriten_netbox/models.py
kriten_netbox/navigation.py
kriten_netbox/services.py
kriten_netbox/tables.py
kriten_netbox/urls.py
kriten_netbox/views.py
kriten_netbox/api/__init__.py
kriten_netbox/api/serializers.py
kriten_netbox/api/urls.py
kriten_netbox/api/views.py
kriten_netbox/migrations/0001_initial.py
kriten_netbox/migrations/__init__.py
kriten_netbox/templates/kriten_netbox/delete_form.html
kriten_netbox/templates/kriten_netbox/kritencluster.html
kriten_netbox/templates/kriten_netbox/kritenjob.html
kriten_netbox/templates/kriten_netbox/kritenjobform.html
kriten_netbox/templates/kriten_netbox/kritenrunner.html
kriten_netbox/templates/kriten_netbox/kritentask.html
kriten_netbox/templates/kriten_netbox/object_delete.html
kriten_netbox-0.1.4.dist-info/LICENSE
kriten_netbox-0.1.4.dist-info/METADATA
kriten_netbox-0.1.4.dist-info/WHEEL
kriten_netbox-0.1.4.dist-info/top_level.txt
kriten_netbox-0.1.4.dist-info/RECORD
