Metadata-Version: 2.1
Name: kriten-netbox
Version: 0.1.4
Summary: Configure Kriten and run jobs from NetBox.
Author: Steve Corp
Author-email: steve@kubecode.io
License: Apache License
Project-URL: repository, https://github.com/kriten-io/kriten-netbox-plugin/
Project-URL: homepage, https://kriten.io/
Project-URL: documentation, https://kriten.io/
Keywords: netbox,netbox-plugin,automation,network,network-automation,kubernetes
Classifier: Framework :: Django
Classifier: Programming Language :: Python :: 3
Classifier: Programming Language :: Python :: 3 :: Only
Classifier: Programming Language :: Python :: 3.10
Classifier: Programming Language :: Python :: 3.11
Classifier: Programming Language :: Python :: 3.12
Classifier: Topic :: Software Development :: Libraries :: Python Modules
Requires-Python: >=3.10
License-File: LICENSE
